baltimorestrings/argparse_showhelp/__init__.py
baltimorestrings/argparse_showhelp/argparse_help_on_error.py
baltimorestrings/argparse_showhelp/quick_args.py
baltimorestrings.argparse_showhelp-0.1.1.dist-info/LICENSE
baltimorestrings.argparse_showhelp-0.1.1.dist-info/METADATA
baltimorestrings.argparse_showhelp-0.1.1.dist-info/WHEEL
baltimorestrings.argparse_showhelp-0.1.1.dist-info/top_level.txt
baltimorestrings.argparse_showhelp-0.1.1.dist-info/RECORD
